agentic_evidence_sdk/__init__.py
agentic_evidence_sdk/client.py
agentic_evidence_sdk/exceptions.py
agentic_evidence_sdk/utils.py
agentic_evidence_sdk-0.1.0.dist-info/licenses/LICENSE
agentic_evidence_sdk-0.1.0.dist-info/licenses/NOTICE
agentic_evidence_sdk-0.1.0.dist-info/METADATA
agentic_evidence_sdk-0.1.0.dist-info/WHEEL
agentic_evidence_sdk-0.1.0.dist-info/top_level.txt
agentic_evidence_sdk-0.1.0.dist-info/RECORD
