Metadata-Version: 2.4
Name: agentic-evidence-sdk
Version: 0.1.0
Summary: Python SDK for Agentic Evidence Logger
Author: Rajeshwar Dhayalan
License: Apache License
Project-URL: Homepage, https://rajeshwar77.github.io/open-agent-evidence-docs/
Project-URL: Repository, https://github.com/Rajeshwar77/open-agent-evidence
Project-URL: Documentation, https://rajeshwar77.github.io/open-agent-evidence-docs/
Project-URL: Changelog, https://github.com/Rajeshwar77/open-agent-evidence-docs/blob/main/docs/RELEASE-NOTES.md
Keywords: ai,agentic,evidence,sdk,logging
Classifier: Development Status :: 3 - Alpha
Classifier: License :: OSI Approved :: Apache Software License
Classifier: Programming Language :: Python :: 3
Classifier: Programming Language :: Python :: 3 :: Only
Classifier: Programming Language :: Python :: 3.10
Classifier: Programming Language :: Python :: 3.11
Classifier: Programming Language :: Python :: 3.12
Requires-Python: >=3.10
License-File: LICENSE
License-File: NOTICE
Requires-Dist: pydantic>=2.0
Provides-Extra: dev
Requires-Dist: build; extra == "dev"
Requires-Dist: twine; extra == "dev"
Requires-Dist: pytest; extra == "dev"
Requires-Dist: ruff; extra == "dev"
Requires-Dist: mypy; extra == "dev"
Dynamic: license-file
